[
  {
    "ipv6_prefix": "2600:1f19:8000::/36",
    "region": "us-east-1",
    "service": "EC2",
    "network_border_group": "us-east-1-pilot-3"
  },
  {
    "ipv6_prefix": "2600:1f11:8000::/36",
    "region": "us-east-1",
    "service": "EC2",
    "network_border_group": "us-east-1-pilot-4"
  },
  {
    "ipv6_prefix": "2600:1ff1:8000::/39",
    "region": "us-east-1",
    "service": "EC2",
    "network_border_group": "us-east-1"
  },
  {
    "ipv6_prefix": "2600:1f18::/33",
    "region": "us-east-1",
    "service": "EC2",
    "network_border_group": "us-east-1"
  },
  {
    "ipv6_prefix": "2600:1ffd:807f::/48",
    "region": "us-east-1",
    "service": "EC2",
    "network_border_group": "us-east-1"
  },
  {
    "ipv6_prefix": "2600:1f1a:8000::/36",
    "region": "us-east-1",
    "service": "EC2",
    "network_border_group": "us-east-1-wl1-mia-wlz-1"
  },
  {
    "ipv6_prefix": "2606:f40:3001::/48",
    "region": "us-east-1",
    "service": "EC2",
    "network_border_group": "us-east-1"
  },
  {
    "ipv6_prefix": "2600:1ffd:807b::/48",
    "region": "us-east-1",
    "service": "EC2",
    "network_border_group": "us-east-1"
  },
  {
    "ipv6_prefix": "2606:f40::/48",
    "region": "us-east-1",
    "service": "EC2",
    "network_border_group": "us-east-1"
  },
  {
    "ipv6_prefix": "2600:1ff0:8000::/39",
    "region": "us-east-1",
    "service": "EC2",
    "network_border_group": "us-east-1"
  },
  {
    "ipv6_prefix": "2600:1f70:8000::/40",
    "region": "us-east-1",
    "service": "EC2",
    "network_border_group": "us-east-1"
  },
  {
    "ipv6_prefix": "2600:1f1f:8000::/36",
    "region": "us-east-1",
    "service": "EC2",
    "network_border_group": "us-east-1-wl1-atl-wlz-1"
  },
  {
    "ipv6_prefix": "2600:1f13:8000::/36",
    "region": "us-east-1",
    "service": "EC2",
    "network_border_group": "us-east-1-pilot-1"
  },
  {
    "ipv6_prefix": "2600:1f1c:8000::/36",
    "region": "us-east-1",
    "service": "EC2",
    "network_border_group": "us-east-1-wl1-dfw-wlz-1"
  },
  {
    "ipv6_prefix": "2600:1ffd:803f::/48",
    "region": "us-east-1",
    "service": "EC2",
    "network_border_group": "us-east-1"
  },
  {
    "ipv6_prefix": "2600:1f15:8000::/36",
    "region": "us-east-1",
    "service": "EC2",
    "network_border_group": "us-east-1-pilot-5"
  },
  {
    "ipv6_prefix": "2600:1f17:8000::/36",
    "region": "us-east-1",
    "service": "EC2",
    "network_border_group": "us-east-1-wl1-nyc-wlz-1"
  },
  {
    "ipv6_prefix": "2600:1fff:8000::/40",
    "region": "us-east-1",
    "service": "EC2",
    "network_border_group": "us-east-1"
  },
  {
    "ipv6_prefix": "2600:1f10:8000::/36",
    "region": "us-east-1",
    "service": "EC2",
    "network_border_group": "us-east-1-wl1-bos-wlz-1"
  },
  {
    "ipv6_prefix": "2406:da00:ff00::/64",
    "region": "us-east-1",
    "service": "EC2",
    "network_border_group": "us-east-1"
  },
  {
    "ipv6_prefix": "2600:1f60:8000::/39",
    "region": "us-east-1",
    "service": "EC2",
    "network_border_group": "us-east-1"
  },
  {
    "ipv6_prefix": "2600:1ffd:8066::/48",
    "region": "us-east-1",
    "service": "EC2",
    "network_border_group": "us-east-1"
  },
  {
    "ipv6_prefix": "2600:1f00:8000::/40",
    "region": "us-east-1",
    "service": "EC2",
    "network_border_group": "us-east-1"
  },
  {
    "ipv6_prefix": "2600:1f18:8000::/36",
    "region": "us-east-1",
    "service": "EC2",
    "network_border_group": "us-east-1-wl1-was-wlz-1"
  },
  {
    "ipv6_prefix": "2620:107:4007::/64",
    "region": "us-east-1",
    "service": "EC2",
    "network_border_group": "us-east-1"
  }
]